ALU.sv
module ALU #(
    parameter 
                    ADDRESS_WIDTH =3,
                    DATA_WIDTH = 32
)(
    input logic [DATA_WIDTH-1:0]        ALUop1,
    input logic [DATA_WIDTH-1:0]        ALUop2,
    input logic [ADDRESS_WIDTH-1:0]     ALUctrlCU,
    output logic [DATA_WIDTH-1:0]       Sum,
    output logic                        EQ
);

    always_comb begin
        case(ALUctrlCU)
            3'b000: Sum = ALUop1+ALUop2;
            //3'b001: ALUout = ALUop1-ALUop2;
            //3'b010: ALUout = ALUop1 && ALUop2;
            //3'b011: ALUout = ALUop1 || ALUop2;
            //3'b101 ALUout = SLT?
            default: begin
                Sum = 0;
                $display("invalid"); //not valid opcode 
            end
        endcase
    end 
   
    always EQ = ALUop1 == ALUop2;

endmodule

ALUsrc.sv
module ALUsrc #(
    parameter DATA_WIDTH = 32

)(
    input logic [DATA_WIDTH-1:0]        regOp2,
    input logic [DATA_WIDTH-1:0]        ImmOp,
    input logic                         ALUsrc,
    output logic [DATA_WIDTH-1:0]       ALUop2
);

assign ALUop2 = ALUsrc ? ImmOp : regOp2;


endmodule

lab1/datamem.sv
module datamem#(
    parameter  ADDRESS_WIDTH = 20,
               DATA_WIDTH = 32
)(
    input logic             clk,
    input logic             we,
    input logic  [ADDRESS_WIDTH-1:0]  a,
    input logic   [DATA_WIDTH-1:0] wd,
    output logic [DATA_WIDTH-1:0] ReadData
);

logic [7:0] data_mem_array [2**ADDRESS_WIDTH-1:0]; //32x32 bit memory

//purely combinational only loading 

initial begin
        $display("Loading mem.");
        $readmemh("datamem.mem", data_mem_array);
end

always_ff @(posedge clk)
    if (we) begin
        data_mem_array[a+3] <= wd[7:0]; 
        data_mem_array[a+2] <= wd[15:8]; 
        data_mem_array[a+1] <= wd[23:16]; 
        data_mem_array[a]   <= wd[31:24]; 
    end

assign ReadData = {data_mem_array[a],data_mem_array[a+1],data_mem_array[a+2],data_mem_array[a+3]}; //32 bit word address, shift the bits by 2 to divide by 4

endmodule

signextend.sv
module signextend(
  input logic [31:0] instr,
  input logic ImmSrc,
  output reg [31:0] ImmOp
);

//wire [12:0] _unused_ok = instr[24:12];

always_comb 
  case 
    ImmOp = ImmSrc ? {{20{instr[31]}},{instr[7]},{instr[30:25]},{instr[11:8]}, 1'b0} : {{20{instr[31]}},{instr[11:7]},{instr[6:0]}};
    default: ImmOp = {32{1'b0}};
  endcase 
endmodule

regfile.sv
module regfile#(
    parameter A_WIDTH = 5,
              D_WIDTH = 32
)(
    input logic  [A_WIDTH-1:0]       rs1, //AD1
    input logic  [A_WIDTH-1:0]       rs2, //AD2
    input logic [A_WIDTH-1:0]        rd,  //AD3
    input logic                     clk,
    input logic                     RegWrite, //WE3
    input logic  [D_WIDTH-1:0]      write_data3,  //WD3
    output logic [D_WIDTH-1:0]      rd1, //RD1
    output logic [D_WIDTH-1:0]      rd2, //RD2
    output logic [D_WIDTH-1:0]      a0 // reg10...return value is loaded here so the TB can inspect the state of the CPU (see value of a0)

);

//include rst 

logic [D_WIDTH-1:0] mem_array [2**A_WIDTH-1:0];  //CHECK??????????????????? (32x32 bit reg?)


//synchronus write
always_ff @(posedge clk) begin 

    if (RegWrite)
        mem_array[rd] <= write_data3;
end

//asynchronus read
always_comb 
    begin
        a0 = mem_array[5'd10]; //return value loaded here
        //mem_array[0] = 0;
        //rd1 = mem_array[rs1];
        //rd2 = mem_array[rs2];
    end

always rd1=mem_array[rs1];
always rd2=rs2;

assign mem_array[0] = 0;
assign mem_array[1] = 1;

endmodule

controlunit.sv
module controlunit(
    input  logic [31:0] instr,
    input  logic EQ,
    output logic MemWrite,
    output logic RegWrite,
    output logic [2:0] ALUctrl,
    output logic ALUsrc,
    output logic ImmSrc, //1
    output logic PCsrc,
    output logic ResultSrc
);

wire [21:0] _unused = {instr[31:15], instr[11:7]};

always_comb
    begin
        RegWrite = 0; ALUctrl = 0; ALUsrc = 1; ImmSrc = 0; PCsrc = 0; MemWrite = 0; ResultSrc = 0;//default bne
        if (instr[6:0] == 7'b1100011 && instr[14:12] == 3'b1) // branch - bne but inputs are equal
        begin 
            ImmSrc = 1; 
            ALUsrc = 0;
            if (!EQ) 
            begin    
                PCsrc = 1; 
            end
        end

        else if (instr[6:0] == 7'b0000011)
        begin 
            // load word instruction
            MemWrite = 1;
            ResultSrc = 1;
        end

        else if (instr[6:0] == 7'h13 && instr[14:12] == 3'b0) // addi 
        begin
            RegWrite =1; 
            ImmSrc = 0;
            PCsrc = 0;
        end
    end 

endmodule

//PUT IN EQ CONDITION FOR THE BNE !!!!!!!!!!!!!!!!!!!!!!!!!!!!!!!!!!!!!!!!!!!!!!!!!!!!!!!!!11
//right now it sees its a bne instr and just branches whether or not condition is chgit config ecked.

instrmem.sv
module instrmem #(
        parameter   ADDRESS_WIDTH =8,
                    DATA_WIDTH =32
)(

    input logic [DATA_WIDTH-1:0] PC,
    output logic [DATA_WIDTH-1:0] Instr
);

logic [DATA_WIDTH-1:0] rom_array [2**ADDRESS_WIDTH-1:0];

initial begin
        $display("Loading rom.");
        $readmemh("instrmem.mem", rom_array);
end;

assign Instr = rom_array [PC>>2]; //32 bit word address, shift the bits by 2 to divide by 4

endmodule

pc.sv
module pc#(
    parameter D_WIDTH = 32
)(

    input logic        [D_WIDTH-1:0]       ImmOp,
    input logic                            clk,
    input logic                            rst,
    input logic                            PCsrc,
    output logic       [D_WIDTH-1:0]       PC
);

    logic               [D_WIDTH-1:0]    branch_PC;
    logic               [D_WIDTH-1:0]    inc_PC;
    logic               [D_WIDTH-1:0]    next_PC;
    
    
    always_ff @(posedge clk) begin
        if (rst) PC <= 0; 
        else PC <= next_PC;
    end
    
    
    always_comb begin
        branch_PC = PC + ImmOp;
        inc_PC = PC + 4;
        next_PC = PCsrc ? branch_PC : inc_PC; 
    end

    
endmodule

top.sv
module top#(
    parameter WIDTH = 32
    //parameter A_WIDTH = 5
)(
    input logic clk,
    input logic rst,
    output logic [WIDTH-1:0] a0
);

always_comb 
    $display("a0: ", a0);

// logic        [2:0]               _unused_top;

logic       [WIDTH-1:0]          ImmOp;
logic       [WIDTH-1:0]         PC;
logic       [WIDTH-1:0]         Instr;
logic                           EQ;
logic       [WIDTH-1:0]         Result;
logic                           ResultSrc;
logic                           RegWrite;
logic       [2:0]             ALUctrlCU;
logic                           ALUsrc;
// logic                        sum;
logic                           ImmSrc;
logic                           PCsrc;
//logic       [A_WIDTH-1:0]     rd;
logic [WIDTH-1:0]               rd1 ; // wire connecting RD1 output to ALUop1
logic [WIDTH-1:0]               rd2 ; // wire connecting RD2 output to multiplexer
logic [WIDTH-1:0]               ALUop2 ; // wire connecting multiplexer into input of ALU
logic [WIDTH-1:0]               ALUresult ; // wire connecting output of ALU to regfile WD3
logic [WIDTH-1:0]               ReadData;
logic                           MemWrite; // data_mem write enable

pc pcreg(
    .clk(clk),
    .rst(rst),
    .PCsrc(PCsrc),
    .ImmOp(ImmOp),
    .PC(PC)
);

// pcreg register(
//         .clk(clk),
//         .rst(rst),
//         .next_PC(PC),
//         .PC(PC)
// );

instrmem instrmem(
    .PC(PC),
    .Instr(Instr)
);

//assign rd1 = Instr[19:15];
//assign rd2 = Instr[24:20];
//assign Instr = Instr[11:7];

controlunit CU(
    .ResultSrc(ResultSrc),
    .instr(Instr),
    .EQ(EQ),
    .MemWrite(MemWrite),
    .RegWrite(RegWrite),
    .ALUctrl(ALUctrlCU),
    .ALUsrc(ALUsrc),
    .ImmSrc(ImmSrc),
    .PCsrc(PCsrc)
);

//result mux
assign Result = ResultSrc ? ReadData : ALUresult;

regfile read_data1 (
    .clk(clk),
    //.rst(rst), need to include
    .rd1(rd1),
    .rs1(Instr[19:15]),
    .rs2(Instr[24:20]),
    .rd(Instr[11:7]),
    .RegWrite(RegWrite),
    .write_data3(Result),
    .rd2(rd2), 
    .a0(a0)
);

signextend SignExt(
    .instr(Instr),
    .ImmOp(ImmOp),
    .ImmSrc(ImmSrc)
);

datamem DataMem(
    .clk(clk),
    .a(ALUresult[19:0]),
    .ReadData(ReadData),
    .we(MemWrite),
    .wd(rd2)
);

ALUsrc src(
    .regOp2(rd2),
    .ALUsrc(ALUsrc),
    .ImmOp(ImmOp),
    .ALUop2(ALUop2) // ALUop2
);

ALU alu(
    .ALUctrlCU(ALUctrlCU),
    .ALUop1(rd1),
    .ALUop2(ALUop2), // ALUop2
    .Sum(ALUresult),
    .EQ(EQ)
);

endmodule

top.vcd
$version Generated by VerilatedVcd $end
$date Sun Nov 27 00:34:46 2022 $end
$timescale 1ps $end

 $scope module TOP $end
  $var wire 32 x a0 [31:0] $end
  $var wire  1 v clk $end
  $var wire  1 w rst $end
  $scope module top $end
   $var wire  3 z ALUctrlCU [2:0] $end
   $var wire 32 K ALUop2 [31:0] $end
   $var wire 32 L ALUresult [31:0] $end
   $var wire  1 F ALUsrc $end
   $var wire  1 B EQ $end
   $var wire 32 ? ImmOp [31:0] $end
   $var wire  1 G ImmSrc $end
   $var wire 32 A Instr [31:0] $end
   $var wire  1 N MemWrite $end
   $var wire 32 @ PC [31:0] $end
   $var wire  1 H PCsrc $end
   $var wire 32 M ReadData [31:0] $end
   $var wire  1 E RegWrite $end
   $var wire 32 C Result [31:0] $end
   $var wire  1 D ResultSrc $end
   $var wire 32 y WIDTH [31:0] $end
   $var wire 32 x a0 [31:0] $end
   $var wire  1 v clk $end
   $var wire 32 I rd1 [31:0] $end
   $var wire 32 J rd2 [31:0] $end
   $var wire  1 w rst $end
   $scope module CU $end
    $var wire  3 z ALUctrl [2:0] $end
    $var wire  1 F ALUsrc $end
    $var wire  1 B EQ $end
    $var wire  1 G ImmSrc $end
    $var wire  1 N MemWrite $end
    $var wire  1 H PCsrc $end
    $var wire  1 E RegWrite $end
    $var wire  1 D ResultSrc $end
    $var wire 32 A instr [31:0] $end
   $upscope $end
   $scope module DataMem $end
    $var wire 32 { ADDRESS_WIDTH [31:0] $end
    $var wire 32 y DATA_WIDTH [31:0] $end
    $var wire 32 M ReadData [31:0] $end
    $var wire 20 O a [19:0] $end
    $var wire  1 v clk $end
    $var wire 32 J wd [31:0] $end
    $var wire  1 N we $end
   $upscope $end
   $scope module SignExt $end
    $var wire 32 ? ImmOp [31:0] $end
    $var wire  1 G ImmSrc $end
    $var wire 32 A instr [31:0] $end
   $upscope $end
   $scope module alu $end
    $var wire 32 | ADDRESS_WIDTH [31:0] $end
    $var wire  3 z ALUctrlCU [2:0] $end
    $var wire 32 I ALUop1 [31:0] $end
    $var wire 32 K ALUop2 [31:0] $end
    $var wire 32 y DATA_WIDTH [31:0] $end
    $var wire  1 B EQ $end
    $var wire 32 L Sum [31:0] $end
   $upscope $end
   $scope module instrmem $end
    $var wire 32 y ADDRESS_WIDTH [31:0] $end
    $var wire 32 } DATA_WIDTH [31:0] $end
    $var wire 32 A Instr [31:0] $end
    $var wire 32 @ PC [31:0] $end
    $var wire  8 # rom_array[0] [7:0] $end
    $var wire  8 - rom_array[10] [7:0] $end
    $var wire  8 . rom_array[11] [7:0] $end
    $var wire  8 / rom_array[12] [7:0] $end
    $var wire  8 0 rom_array[13] [7:0] $end
    $var wire  8 1 rom_array[14] [7:0] $end
    $var wire  8 2 rom_array[15] [7:0] $end
    $var wire  8 3 rom_array[16] [7:0] $end
    $var wire  8 4 rom_array[17] [7:0] $end
    $var wire  8 5 rom_array[18] [7:0] $end
    $var wire  8 6 rom_array[19] [7:0] $end
    $var wire  8 $ rom_array[1] [7:0] $end
    $var wire  8 7 rom_array[20] [7:0] $end
    $var wire  8 8 rom_array[21] [7:0] $end
    $var wire  8 9 rom_array[22] [7:0] $end
    $var wire  8 : rom_array[23] [7:0] $end
    $var wire  8 ; rom_array[24] [7:0] $end
    $var wire  8 < rom_array[25] [7:0] $end
    $var wire  8 = rom_array[26] [7:0] $end
    $var wire  8 > rom_array[27] [7:0] $end
    $var wire  8 % rom_array[2] [7:0] $end
    $var wire  8 & rom_array[3] [7:0] $end
    $var wire  8 ' rom_array[4] [7:0] $end
    $var wire  8 ( rom_array[5] [7:0] $end
    $var wire  8 ) rom_array[6] [7:0] $end
    $var wire  8 * rom_array[7] [7:0] $end
    $var wire  8 + rom_array[8] [7:0] $end
    $var wire  8 , rom_array[9] [7:0] $end
   $upscope $end
   $scope module pcreg $end
    $var wire 32 y D_WIDTH [31:0] $end
    $var wire 32 ? ImmOp [31:0] $end
    $var wire 32 @ PC [31:0] $end
    $var wire  1 H PCsrc $end
    $var wire 32 P branch_PC [31:0] $end
    $var wire  1 v clk $end
    $var wire 32 Q inc_PC [31:0] $end
    $var wire 32 R next_PC [31:0] $end
    $var wire  1 w rst $end
   $upscope $end
   $scope module read_data1 $end
    $var wire 32 ~ A_WIDTH [31:0] $end
    $var wire 32 y D_WIDTH [31:0] $end
    $var wire  1 E RegWrite $end
    $var wire 32 x a0 [31:0] $end
    $var wire  1 v clk $end
    $var wire 32 V mem_array[0] [31:0] $end
    $var wire 32 ` mem_array[10] [31:0] $end
    $var wire 32 a mem_array[11] [31:0] $end
    $var wire 32 b mem_array[12] [31:0] $end
    $var wire 32 c mem_array[13] [31:0] $end
    $var wire 32 d mem_array[14] [31:0] $end
    $var wire 32 e mem_array[15] [31:0] $end
    $var wire 32 f mem_array[16] [31:0] $end
    $var wire 32 g mem_array[17] [31:0] $end
    $var wire 32 h mem_array[18] [31:0] $end
    $var wire 32 i mem_array[19] [31:0] $end
    $var wire 32 W mem_array[1] [31:0] $end
    $var wire 32 j mem_array[20] [31:0] $end
    $var wire 32 k mem_array[21] [31:0] $end
    $var wire 32 l mem_array[22] [31:0] $end
    $var wire 32 m mem_array[23] [31:0] $end
    $var wire 32 n mem_array[24] [31:0] $end
    $var wire 32 o mem_array[25] [31:0] $end
    $var wire 32 p mem_array[26] [31:0] $end
    $var wire 32 q mem_array[27] [31:0] $end
    $var wire 32 r mem_array[28] [31:0] $end
    $var wire 32 s mem_array[29] [31:0] $end
    $var wire 32 X mem_array[2] [31:0] $end
    $var wire 32 t mem_array[30] [31:0] $end
    $var wire 32 u mem_array[31] [31:0] $end
    $var wire 32 Y mem_array[3] [31:0] $end
    $var wire 32 Z mem_array[4] [31:0] $end
    $var wire 32 [ mem_array[5] [31:0] $end
    $var wire 32 \ mem_array[6] [31:0] $end
    $var wire 32 ] mem_array[7] [31:0] $end
    $var wire 32 ^ mem_array[8] [31:0] $end
    $var wire 32 _ mem_array[9] [31:0] $end
    $var wire  5 U rd [4:0] $end
    $var wire 32 I rd1 [31:0] $end
    $var wire 32 J rd2 [31:0] $end
    $var wire  5 S rs1 [4:0] $end
    $var wire  5 T rs2 [4:0] $end
    $var wire 32 C write_data3 [31:0] $end
   $upscope $end
   $scope module src $end
    $var wire 32 K ALUop2 [31:0] $end
    $var wire  1 F ALUsrc $end
    $var wire 32 y DATA_WIDTH [31:0] $end
    $var wire 32 ? ImmOp [31:0] $end
    $var wire 32 J regOp2 [31:0] $end
   $upscope $end
  $upscope $end
 $upscope $end
$enddefinitions $end


#0
b00000000 #
b00000000 $
b00000000 %
b00000000 &
b00000000 '
b00000000 (
b00000000 )
b00000000 *
b00000000 +
b00000000 ,
b00000000 -
b00000000 .
b00000000 /
b00000000 0
b00000000 1
b00000000 2
b00000000 3
b00000000 4
b00000000 5
b00000000 6
b00000000 7
b00000000 8
b00000000 9
b00000000 :
b00000000 ;
b00000000 <
b00000000 =
b00000000 >
b00000000000000000000000000000000 ?
b00000000000000000000000000000000 @
b00000000000000000000000000000000 A
1B
b00000000000000000000000000000000 C
0D
0E
0F
0G
0H
b00000000000000000000000000000000 I
b00000000000000000000000000000000 J
b00000000000000000000000000000000 K
b00000000000000000000000000000000 L
b00000000000000000000000000000000 M
0N
b00000000000000000000 O
b00000000000000000000000000000000 P
b00000000000000000000000000000000 Q
b00000000000000000000000000000000 R
b00000 S
b00000 T
b00000 U
b00000000000000000000000000000000 V
b00000000000000000000000000000000 W
b00000000000000000000000000000000 X
b00000000000000000000000000000000 Y
b00000000000000000000000000000000 Z
b00000000000000000000000000000000 [
b00000000000000000000000000000000 \
b00000000000000000000000000000000 ]
b00000000000000000000000000000000 ^
b00000000000000000000000000000000 _
b00000000000000000000000000000000 `
b00000000000000000000000000000000 a
b00000000000000000000000000000000 b
b00000000000000000000000000000000 c
b00000000000000000000000000000000 d
b00000000000000000000000000000000 e
b00000000000000000000000000000000 f
b00000000000000000000000000000000 g
b00000000000000000000000000000000 h
b00000000000000000000000000000000 i
b00000000000000000000000000000000 j
b00000000000000000000000000000000 k
b00000000000000000000000000000000 l
b00000000000000000000000000000000 m
b00000000000000000000000000000000 n
b00000000000000000000000000000000 o
b00000000000000000000000000000000 p
b00000000000000000000000000000000 q
b00000000000000000000000000000000 r
b00000000000000000000000000000000 s
b00000000000000000000000000000000 t
b00000000000000000000000000000000 u
0v
0w
b00000000000000000000000000000000 x
b00000000000000000000000000100000 y
b000 z
b00000000000000000000000000010100 {
b00000000000000000000000000000011 |
b00000000000000000000000000001000 }
b00000000000000000000000000000101 ~
#1
b00001111 #
b11110000 $
b00000011 %
b00010011 &
b00000101 )
b00010011 *
b00000101 -
b10010011 .
b00000101 0
b10000101 1
b00010011 2
b00010101 4
b10000101 5
b10010011 6
b11111110 7
b01100101 8
b10011000 9
b11100011 :
b11111110 ;
b00000011 <
b00010000 =
b11100011 >
b00000000000000000000000011111111 ?
b00001111111100000000001100010011 A
0B
b00000000000000000000000011111111 C
1E
1F
b00000000000000000000000011111111 K
b00000000000000000000000011111111 L
b10000010000000000000000000000000 M
b00000000000011111111 O
b00000000000000000000000011111111 P
b00000000000000000000000000000100 Q
b00000000000000000000000000000100 R
b11111 T
b00110 U
1v
#2
0v
#3
b00000000000000000000000000000000 ?
b00000000000000000000000000000100 @
b00000000000000000000010100010011 A
1B
b00000000000000000000000000000000 C
b00000000000000000000000000000000 K
b00000000000000000000000000000000 L
b00000000000000000000000011111110 M
b00000000000000000000 O
b00000000000000000000000000000100 P
b00000000000000000000000000001000 Q
b00000000000000000000000000001000 R
b00000 T
b01010 U
b00000000000000000000000011111111 \
1v
#4
0v
#5
b00000000000000000000000000001000 @
b00000000000000000000010110010011 A
b00000000000000000000000000001000 P
b00000000000000000000000000001100 Q
b00000000000000000000000000001100 R
b01011 U
1v
#6
0v
#7
b00000000000000000000000000001100 @
b00000000000001011000010100010011 A
b00000000000000000000000000001100 P
b00000000000000000000000000010000 Q
b00000000000000000000000000010000 R
b01011 S
b01010 U
1v
#8
0v
#9
b00000000000000000000000000000001 ?
b00000000000000000000000000010000 @
b00000000000101011000010110010011 A
0B
b00000000000000000000000000000001 C
b00000000000000000000000000000001 K
b00000000000000000000000000000001 L
b00000000000000001111111000000000 M
b00000000000000000001 O
b00000000000000000000000000010001 P
b00000000000000000000000000010100 Q
b00000000000000000000000000010100 R
b00001 T
b01011 U
1v
#10
0v
#11
b11111111111111111111111111111000 ?
b00000000000000000000000000010100 @
b11111110011001011001100011100011 A
b00000000000000000000000100000000 C
0E
0F
1G
1H
b00000000000000000000000000000001 I
b00000000000000000000000011111111 J
b00000000000000000000000011111111 K
b00000000000000000000000100000000 L
b00000000000000000000000001111110 M
b00000000000100000000 O
b00000000000000000000000000001100 P
b00000000000000000000000000011000 Q
b00000000000000000000000000001100 R
b00110 T
b10001 U
b00000000000000000000000000000001 a
1v
#12
0v
#13
b00000000000000000000000000000000 ?
b00000000000000000000000000001100 @
b00000000000001011000010100010011 A
b00000000000000000000000000000001 C
1E
1F
0G
0H
b00000000000000000000000000000000 J
b00000000000000000000000000000000 K
b00000000000000000000000000000001 L
b00000000000000001111111000000000 M
b00000000000000000001 O
b00000000000000000000000000010000 Q
b00000000000000000000000000010000 R
b00000 T
b01010 U
1v
#14
0v
#15
b00000000000000000000000000000001 ?
b00000000000000000000000000010000 @
b00000000000101011000010110010011 A
1B
b00000000000000000000000000000010 C
b00000000000000000000000000000001 K
b00000000000000000000000000000010 L
b00000000111111100000000000000000 M
b00000000000000000010 O
b00000000000000000000000000010001 P
b00000000000000000000000000010100 Q
b00000000000000000000000000010100 R
b00001 T
b01011 U
b00000000000000000000000000000001 `
1v
b00000000000000000000000000000001 x
#16
0v
#17
b11111111111111111111111111111000 ?
b00000000000000000000000000010100 @
b11111110011001011001100011100011 A
0B
b00000000000000000000000100000001 C
0E
0F
1G
1H
b00000000000000000000000000000010 I
b00000000000000000000000011111111 J
b00000000000000000000000011111111 K
b00000000000000000000000100000001 L
b00000000000000000111111000000000 M
b00000000000100000001 O
b00000000000000000000000000001100 P
b00000000000000000000000000011000 Q
b00000000000000000000000000001100 R
b00110 T
b10001 U
b00000000000000000000000000000010 a
1v
#18
0v
#19
b00000000000000000000000000000000 ?
b00000000000000000000000000001100 @
b00000000000001011000010100010011 A
b00000000000000000000000000000010 C
1E
1F
0G
0H
b00000000000000000000000000000000 J
b00000000000000000000000000000000 K
b00000000000000000000000000000010 L
b00000000111111100000000000000000 M
b00000000000000000010 O
b00000000000000000000000000010000 Q
b00000000000000000000000000010000 R
b00000 T
b01010 U
1v
#20
0v
#21
b00000000000000000000000000000001 ?
b00000000000000000000000000010000 @
b00000000000101011000010110010011 A
b00000000000000000000000000000011 C
b00000000000000000000000000000001 K
b00000000000000000000000000000011 L
b11111110000000000000000000000000 M
b00000000000000000011 O
b00000000000000000000000000010001 P
b00000000000000000000000000010100 Q
b00000000000000000000000000010100 R
b00001 T
b01011 U
b00000000000000000000000000000010 `
1v
b00000000000000000000000000000010 x
#22
0v
#23
b11111111111111111111111111111000 ?
b00000000000000000000000000010100 @
b11111110011001011001100011100011 A
b00000000000000000000000100000010 C
0E
0F
1G
1H
b00000000000000000000000000000011 I
b00000000000000000000000011111111 J
b00000000000000000000000011111111 K
b00000000000000000000000100000010 L
b00000000011111100000000000000000 M
b00000000000100000010 O
b00000000000000000000000000001100 P
b00000000000000000000000000011000 Q
b00000000000000000000000000001100 R
b00110 T
b10001 U
b00000000000000000000000000000011 a
1v
#24
0v
#25
b00000000000000000000000000000000 ?
b00000000000000000000000000001100 @
b00000000000001011000010100010011 A
b00000000000000000000000000000011 C
1E
1F
0G
0H
b00000000000000000000000000000000 J
b00000000000000000000000000000000 K
b00000000000000000000000000000011 L
b11111110000000000000000000000000 M
b00000000000000000011 O
b00000000000000000000000000010000 Q
b00000000000000000000000000010000 R
b00000 T
b01010 U
1v
#26
0v
#27
b00000000000000000000000000000001 ?
b00000000000000000000000000010000 @
b00000000000101011000010110010011 A
b00000000000000000000000000000100 C
b00000000000000000000000000000001 K
b00000000000000000000000000000100 L
b00000000000000000000000011111101 M
b00000000000000000100 O
b00000000000000000000000000010001 P
b00000000000000000000000000010100 Q
b00000000000000000000000000010100 R
b00001 T
b01011 U
b00000000000000000000000000000011 `
1v
b00000000000000000000000000000011 x
#28
0v
#29
b11111111111111111111111111111000 ?
b00000000000000000000000000010100 @
b11111110011001011001100011100011 A
b00000000000000000000000100000011 C
0E
0F
1G
1H
b00000000000000000000000000000100 I
b00000000000000000000000011111111 J
b00000000000000000000000011111111 K
b00000000000000000000000100000011 L
b01111110000000000000000000000000 M
b00000000000100000011 O
b00000000000000000000000000001100 P
b00000000000000000000000000011000 Q
b00000000000000000000000000001100 R
b00110 T
b10001 U
b00000000000000000000000000000100 a
1v
#30
0v
#31
b00000000000000000000000000000000 ?
b00000000000000000000000000001100 @
b00000000000001011000010100010011 A
b00000000000000000000000000000100 C
1E
1F
0G
0H
b00000000000000000000000000000000 J
b00000000000000000000000000000000 K
b00000000000000000000000000000100 L
b00000000000000000000000011111101 M
b00000000000000000100 O
b00000000000000000000000000010000 Q
b00000000000000000000000000010000 R
b00000 T
b01010 U
1v
#32
0v
#33
b00000000000000000000000000000001 ?
b00000000000000000000000000010000 @
b00000000000101011000010110010011 A
b00000000000000000000000000000101 C
b00000000000000000000000000000001 K
b00000000000000000000000000000101 L
b00000000000000001111110100000000 M
b00000000000000000101 O
b00000000000000000000000000010001 P
b00000000000000000000000000010100 Q
b00000000000000000000000000010100 R
b00001 T
b01011 U
b00000000000000000000000000000100 `
1v
b00000000000000000000000000000100 x
#34
0v
#35
b11111111111111111111111111111000 ?
b00000000000000000000000000010100 @
b11111110011001011001100011100011 A
b00000000000000000000000100000100 C
0E
0F
1G
1H
b00000000000000000000000000000101 I
b00000000000000000000000011111111 J
b00000000000000000000000011111111 K
b00000000000000000000000100000100 L
b00000000000000000000000001111011 M
b00000000000100000100 O
b00000000000000000000000000001100 P
b00000000000000000000000000011000 Q
b00000000000000000000000000001100 R
b00110 T
b10001 U
b00000000000000000000000000000101 a
1v
#36
0v
#37
b00000000000000000000000000000000 ?
b00000000000000000000000000001100 @
b00000000000001011000010100010011 A
b00000000000000000000000000000101 C
1E
1F
0G
0H
b00000000000000000000000000000000 J
b00000000000000000000000000000000 K
b00000000000000000000000000000101 L
b00000000000000001111110100000000 M
b00000000000000000101 O
b00000000000000000000000000010000 Q
b00000000000000000000000000010000 R
b00000 T
b01010 U
1v
#38
0v
#39
b00000000000000000000000000000001 ?
b00000000000000000000000000010000 @
b00000000000101011000010110010011 A
b00000000000000000000000000000110 C
b00000000000000000000000000000001 K
b00000000000000000000000000000110 L
b00000000111111010000000000000000 M
b00000000000000000110 O
b00000000000000000000000000010001 P
b00000000000000000000000000010100 Q
b00000000000000000000000000010100 R
b00001 T
b01011 U
b00000000000000000000000000000101 `
1v
b00000000000000000000000000000101 x
#40
0v
#41
b11111111111111111111111111111000 ?
b00000000000000000000000000010100 @
b11111110011001011001100011100011 A
b00000000000000000000000100000101 C
0E
0F
1G
1H
b00000000000000000000000000000110 I
b00000000000000000000000011111111 J
b00000000000000000000000011111111 K
b00000000000000000000000100000101 L
b00000000000000000111101100000000 M
b00000000000100000101 O
b00000000000000000000000000001100 P
b00000000000000000000000000011000 Q
b00000000000000000000000000001100 R
b00110 T
b10001 U
b00000000000000000000000000000110 a
1v
#42
0v
#43
b00000000000000000000000000000000 ?
b00000000000000000000000000001100 @
b00000000000001011000010100010011 A
b00000000000000000000000000000110 C
1E
1F
0G
0H
b00000000000000000000000000000000 J
b00000000000000000000000000000000 K
b00000000000000000000000000000110 L
b00000000111111010000000000000000 M
b00000000000000000110 O
b00000000000000000000000000010000 Q
b00000000000000000000000000010000 R
b00000 T
b01010 U
1v
#44
0v
#45
b00000000000000000000000000000001 ?
b00000000000000000000000000010000 @
b00000000000101011000010110010011 A
b00000000000000000000000000000111 C
b00000000000000000000000000000001 K
b00000000000000000000000000000111 L
b11111101000000000000000000000000 M
b00000000000000000111 O
b00000000000000000000000000010001 P
b00000000000000000000000000010100 Q
b00000000000000000000000000010100 R
b00001 T
b01011 U
b00000000000000000000000000000110 `
1v
b00000000000000000000000000000110 x
#46
0v
#47
b11111111111111111111111111111000 ?
b00000000000000000000000000010100 @
b11111110011001011001100011100011 A
b00000000000000000000000100000110 C
0E
0F
1G
1H
b00000000000000000000000000000111 I
b00000000000000000000000011111111 J
b00000000000000000000000011111111 K
b00000000000000000000000100000110 L
b00000000011110110000000000000000 M
b00000000000100000110 O
b00000000000000000000000000001100 P
b00000000000000000000000000011000 Q
b00000000000000000000000000001100 R
b00110 T
b10001 U
b00000000000000000000000000000111 a
1v
#48
0v
#49
b00000000000000000000000000000000 ?
b00000000000000000000000000001100 @
b00000000000001011000010100010011 A
b00000000000000000000000000000111 C
1E
1F
0G
0H
b00000000000000000000000000000000 J
b00000000000000000000000000000000 K
b00000000000000000000000000000111 L
b11111101000000000000000000000000 M
b00000000000000000111 O
b00000000000000000000000000010000 Q
b00000000000000000000000000010000 R
b00000 T
b01010 U
1v
#50
0v
#51
b00000000000000000000000000000001 ?
b00000000000000000000000000010000 @
b00000000000101011000010110010011 A
b00000000000000000000000000001000 C
b00000000000000000000000000000001 K
b00000000000000000000000000001000 L
b00000000000000000000000011111101 M
b00000000000000001000 O
b00000000000000000000000000010001 P
b00000000000000000000000000010100 Q
b00000000000000000000000000010100 R
b00001 T
b01011 U
b00000000000000000000000000000111 `
1v
b00000000000000000000000000000111 x
#52
0v
#53
b11111111111111111111111111111000 ?
b00000000000000000000000000010100 @
b11111110011001011001100011100011 A
b00000000000000000000000100000111 C
0E
0F
1G
1H
b00000000000000000000000000001000 I
b00000000000000000000000011111111 J
b00000000000000000000000011111111 K
b00000000000000000000000100000111 L
b01111011000000000000000000000000 M
b00000000000100000111 O
b00000000000000000000000000001100 P
b00000000000000000000000000011000 Q
b00000000000000000000000000001100 R
b00110 T
b10001 U
b00000000000000000000000000001000 a
1v
#54
0v
#55
b00000000000000000000000000000000 ?
b00000000000000000000000000001100 @
b00000000000001011000010100010011 A
b00000000000000000000000000001000 C
1E
1F
0G
0H
b00000000000000000000000000000000 J
b00000000000000000000000000000000 K
b00000000000000000000000000001000 L
b00000000000000000000000011111101 M
b00000000000000001000 O
b00000000000000000000000000010000 Q
b00000000000000000000000000010000 R
b00000 T
b01010 U
1v
#56
0v
#57
b00000000000000000000000000000001 ?
b00000000000000000000000000010000 @
b00000000000101011000010110010011 A
b00000000000000000000000000001001 C
b00000000000000000000000000000001 K
b00000000000000000000000000001001 L
b00000000000000001111110100000000 M
b00000000000000001001 O
b00000000000000000000000000010001 P
b00000000000000000000000000010100 Q
b00000000000000000000000000010100 R
b00001 T
b01011 U
b00000000000000000000000000001000 `
1v
b00000000000000000000000000001000 x
#58
0v
